Pythonic/__init__.py
Pythonic/all_mine
Pythonic/all_mine.exe
Pythonic/binancetools.py
Pythonic/config.txt
Pythonic/cpu.txt
Pythonic/debugwindow.py
Pythonic/dropbox.py
Pythonic/element_iconbar.py
Pythonic/elementeditor.py
Pythonic/elementmaster.py
Pythonic/exceptwindow.py
Pythonic/executor.py
Pythonic/info.py
Pythonic/libeay32.dll
Pythonic/main.py
Pythonic/mastertool.py
Pythonic/menubar.py
Pythonic/miner.py
Pythonic/pipe_multiprocessor.py
Pythonic/pools.txt
Pythonic/record_function.py
Pythonic/return.py
Pythonic/script.py
Pythonic/settings.py
Pythonic/storagebar.py
Pythonic/top_menubar.py
Pythonic/workingarea.py
Pythonic/elements/__init__.py
Pythonic/elements/basic_branch.py
Pythonic/elements/basic_operation.py
Pythonic/elements/basic_process.py
Pythonic/elements/basic_return.py
Pythonic/elements/basic_ta.py
Pythonic/elements/basicelements.py
Pythonic/elements/binance_ohlc.py
Pythonic/elements/binance_order.py
Pythonic/elements/binance_sched.py
Pythonic/images/BinanceOHLC.png
Pythonic/images/BinanceOrder.png
Pythonic/images/BinanceSched.png
Pythonic/images/ExecBranch.png
Pythonic/images/ExecOp.png
Pythonic/images/ExecProcess.png
Pythonic/images/ExecReturn.png
Pythonic/images/ExecTA.png
Pythonic/images/debug.png
Pythonic/images/del.png
Pythonic/images/edit.png
Pythonic/images/icon.png
Pythonic/images/logo_rechts.png
Pythonic/images/new_file.png
Pythonic/images/open_file.png
Pythonic/images/pause.png
Pythonic/images/placeholder.png
Pythonic/images/right.png
Pythonic/images/right_bot.png
Pythonic/images/run.png
Pythonic/images/save.png
Pythonic/images/save_as.png
Pythonic/images/start.png
Pythonic/images/start_debug.png
Pythonic/images/stop.png
Pythonic/images/stop_exec.png
Pythonic/images/tmp.png
Pythonic/translations/chinese_cn.qm
Pythonic/translations/cn.png
Pythonic/translations/de.png
Pythonic/translations/en.png
Pythonic/translations/english_en.qm
Pythonic/translations/es.png
Pythonic-0.1.dist-info/METADATA
Pythonic-0.1.dist-info/RECORD
Pythonic-0.1.dist-info/WHEEL
Pythonic-0.1.dist-info/entry_points.txt
Pythonic-0.1.dist-info/top_level.txt
